crawilfy_mcp_server-0.3.4.dist-info/licenses/LICENSE
src/__init__.py
src/cli/__init__.py
src/cli/main.py
src/core/__init__.py
src/core/rate_limiter.py
src/core/recording_storage.py
src/core/browser/__init__.py
src/core/browser/cdp.py
src/core/browser/pool.py
src/core/browser/proxy_pool.py
src/core/browser/stealth.py
src/core/cache/__init__.py
src/core/cache/manager.py
src/core/http/__init__.py
src/core/http/stealth_client.py
src/core/session/__init__.py
src/core/session/manager.py
src/crawlers/__init__.py
src/intelligence/__init__.py
src/intelligence/extraction/__init__.py
src/intelligence/extraction/content.py
src/intelligence/extraction/smart.py
src/intelligence/generator/__init__.py
src/intelligence/generator/crawler_gen.py
src/intelligence/js/__init__.py
src/intelligence/js/analyzer.py
src/intelligence/js/deobfuscator.py
src/intelligence/js/dynamic.py
src/intelligence/network/__init__.py
src/intelligence/network/analyzer.py
src/intelligence/network/api_discovery.py
src/intelligence/network/graphql.py
src/intelligence/network/interceptor.py
src/intelligence/network/sitemap.py
src/intelligence/network/websocket.py
src/intelligence/recorder/__init__.py
src/intelligence/recorder/session.py
src/intelligence/recorder/state_machine.py
src/intelligence/security/__init__.py
src/intelligence/security/auth.py
src/intelligence/security/bot_detection.py
src/intelligence/security/captcha_solver.py
src/intelligence/security/technology_detector.py
src/mcp/__init__.py
src/mcp/config.py
src/mcp/server.py
src/mcp/utils.py
src/mcp/tools/__init__.py
src/sites/__init__.py
crawilfy_mcp_server-0.3.4.dist-info/METADATA
crawilfy_mcp_server-0.3.4.dist-info/WHEEL
crawilfy_mcp_server-0.3.4.dist-info/entry_points.txt
crawilfy_mcp_server-0.3.4.dist-info/top_level.txt
crawilfy_mcp_server-0.3.4.dist-info/RECORD
