Metadata-Version: 2.4
Name: crawilfy-mcp-server
Version: 0.3.4
Summary: Advanced Web Crawling Platform with Deep Analysis and MCP Server
Author-email: "emad.dev" <contact@emad.dev>
License: MIT
Keywords: crawling,scraping,automation,mcp,web-analysis,playwright,api-discovery
Classifier: Development Status :: 4 - Beta
Classifier: Intended Audience :: Developers
Classifier: License :: OSI Approved :: MIT License
Classifier: Programming Language :: Python :: 3
Classifier: Programming Language :: Python :: 3.10
Classifier: Programming Language :: Python :: 3.11
Classifier: Programming Language :: Python :: 3.12
Classifier: Topic :: Internet :: WWW/HTTP :: Browsers
Classifier: Topic :: Software Development :: Libraries :: Python Modules
Classifier: Topic :: System :: Networking
Requires-Python: >=3.10
License-File: LICENSE
Requires-Dist: playwright>=1.40.0
Requires-Dist: mcp>=1.0.0
Requires-Dist: pydantic>=2.0.0
Requires-Dist: aiohttp>=3.9.0
Requires-Dist: httpx>=0.25.0
Requires-Dist: pyyaml>=6.0
Requires-Dist: pydantic-settings>=2.0.0
Requires-Dist: python-json-logger>=2.0.0
Requires-Dist: tenacity>=8.2.0
Requires-Dist: cachetools>=5.3.0
Requires-Dist: graphql-core>=3.2.0
Requires-Dist: esprima>=4.0.0
Requires-Dist: beautifulsoup4>=4.12.0
Requires-Dist: lxml>=5.0.0
Requires-Dist: cryptography>=41.0.0
Requires-Dist: curl-cffi>=0.6.0
Requires-Dist: fake-useragent>=1.4.0
Requires-Dist: trafilatura>=1.6.0
Requires-Dist: selectolax>=0.3.0
Requires-Dist: markdownify>=0.11.0
Requires-Dist: python-anticaptcha>=1.0.0
Requires-Dist: capsolver>=1.0.0
Requires-Dist: instructor>=0.4.0
Requires-Dist: openai>=1.0.0
Requires-Dist: python-Wappalyzer>=0.3.0
Requires-Dist: ftfy>=6.1.0
Requires-Dist: dateparser>=1.2.0
Requires-Dist: url-normalize>=1.4.0
Requires-Dist: tldextract>=5.0.0
Provides-Extra: dev
Requires-Dist: pytest>=7.4.0; extra == "dev"
Requires-Dist: pytest-asyncio>=0.21.0; extra == "dev"
Requires-Dist: black>=23.0.0; extra == "dev"
Requires-Dist: ruff>=0.1.0; extra == "dev"
Requires-Dist: mypy>=1.7.0; extra == "dev"
Dynamic: license-file
